.gitignore
LICENSE
MANIFEST.in
Makefile
README.md
pyproject.toml
setup.cfg
.github/pull_request_template.md
.github/ISSUE_TEMPLATE/bug_report.md
.github/ISSUE_TEMPLATE/feature_request.md
.github/workflows/coverage.yml
.github/workflows/publish_release.yml
.github/workflows/style.yml
src/orquestra/integrations/qiskit/__init__.py
src/orquestra/integrations/qiskit/_get_provider.py
src/orquestra/integrations/qiskit/py.typed
src/orquestra/integrations/qiskit/conversions/__init__.py
src/orquestra/integrations/qiskit/conversions/_circuit_conversions.py
src/orquestra/integrations/qiskit/conversions/_pauli_conversions.py
src/orquestra/integrations/qiskit/conversions/_qiskit_expressions.py
src/orquestra/integrations/qiskit/conversions/_symengine_expressions.py
src/orquestra/integrations/qiskit/noise/__init__.py
src/orquestra/integrations/qiskit/noise/basic.py
src/orquestra/integrations/qiskit/runner/__init__.py
src/orquestra/integrations/qiskit/runner/_ibmq_runner.py
src/orquestra/integrations/qiskit/runner/_qiskit_runner.py
src/orquestra/integrations/qiskit/simulator/__init__.py
src/orquestra/integrations/qiskit/simulator/_qiskit_wavefunction_simulator.py
src/orquestra_qiskit.egg-info/PKG-INFO
src/orquestra_qiskit.egg-info/SOURCES.txt
src/orquestra_qiskit.egg-info/dependency_links.txt
src/orquestra_qiskit.egg-info/not-zip-safe
src/orquestra_qiskit.egg-info/requires.txt
src/orquestra_qiskit.egg-info/top_level.txt
subtrees/z_quantum_actions/MANIFEST.in
subtrees/z_quantum_actions/Makefile
subtrees/z_quantum_actions/README.rst
subtrees/z_quantum_actions/pyproject.toml
subtrees/z_quantum_actions/pytest.ini
subtrees/z_quantum_actions/sample_setup.py
subtrees/z_quantum_actions/setup_extras.py
subtrees/z_quantum_actions/variables.mk
subtrees/z_quantum_actions/actions/coverage/action.yml
subtrees/z_quantum_actions/actions/publish-release/action.yml
subtrees/z_quantum_actions/actions/ssh_setup/action.yml
subtrees/z_quantum_actions/actions/style/action.yml
subtrees/z_quantum_actions/bin/get_next_version.py
subtrees/z_quantum_actions/tests/test_get_next_version.py
subtrees/z_quantum_actions/workflow-templates/coverage.yml
subtrees/z_quantum_actions/workflow-templates/publish_release.yml
subtrees/z_quantum_actions/workflow-templates/style.yml
