Metadata-Version: 2.1
Name: orquestra-qiskit
Version: 0.13.0
Summary: "Orquestra Qiskit package"
Home-page: https://github.com/zapatacomputing/orquestra-qiskit
Author: Zapata Computing Inc.
Author-email: info@zapatacomputing.com,
License: Apache Software License 2.0
Classifier: Programming Language :: Python :: 3
Classifier: Operating System :: OS Independent
Classifier: License :: OSI Approved :: Apache Software License
Classifier: Topic :: Scientific/Engineering
Requires-Python: !=3.9.7,>=3.9
License-File: LICENSE
Requires-Dist: numpy>=1.20
Requires-Dist: scipy>=1.4.1
Requires-Dist: sympy<=1.9,>=1.5
Requires-Dist: qiskit~=0.44.2
Requires-Dist: qiskit-aer~=0.12.2
Requires-Dist: qiskit-ibm-provider~=0.7.0
Requires-Dist: symengine~=0.7
Requires-Dist: orquestra-quantum
Provides-Extra: dev
Requires-Dist: orquestra-python-dev; extra == "dev"
